line_bot_sdk-3.19.2.dist-info/licenses/LICENSE
linebot/__about__.py
linebot/__init__.py
linebot/aiohttp_async_http_client.py
linebot/api.py
linebot/async_api.py
linebot/async_http_client.py
linebot/deprecations.py
linebot/exceptions.py
linebot/http_client.py
linebot/utils.py
linebot/webhook.py
linebot/constants/__init__.py
linebot/constants/postback_input_option.py
linebot/models/__init__.py
linebot/models/actions.py
linebot/models/background.py
linebot/models/base.py
linebot/models/delivery_context.py
linebot/models/emojis.py
linebot/models/error.py
linebot/models/events.py
linebot/models/filter.py
linebot/models/flex_message.py
linebot/models/imagemap.py
linebot/models/insight.py
linebot/models/limit.py
linebot/models/mention.py
linebot/models/mentionee.py
linebot/models/messages.py
linebot/models/operator.py
linebot/models/recipient.py
linebot/models/responses.py
linebot/models/rich_menu.py
linebot/models/send_messages.py
linebot/models/sources.py
linebot/models/template.py
linebot/models/things.py
linebot/models/unsend.py
linebot/models/video_play_complete.py
linebot/v3/__init__.py
linebot/v3/exceptions.py
linebot/v3/utils.py
linebot/v3/webhook.py
linebot/v3/audience/__init__.py
linebot/v3/audience/api_client.py
linebot/v3/audience/api_response.py
linebot/v3/audience/async_api_client.py
linebot/v3/audience/async_rest.py
linebot/v3/audience/configuration.py
linebot/v3/audience/exceptions.py
linebot/v3/audience/rest.py
linebot/v3/audience/api/__init__.py
linebot/v3/audience/api/async_manage_audience.py
linebot/v3/audience/api/async_manage_audience_blob.py
linebot/v3/audience/api/manage_audience.py
linebot/v3/audience/api/manage_audience_blob.py
linebot/v3/audience/models/__init__.py
linebot/v3/audience/models/adaccount.py
linebot/v3/audience/models/add_audience_to_audience_group_request.py
linebot/v3/audience/models/audience.py
linebot/v3/audience/models/audience_group.py
linebot/v3/audience/models/audience_group_create_route.py
linebot/v3/audience/models/audience_group_failed_type.py
line_bot_sdk-3.19.2.dist-info/METADATA
line_bot_sdk-3.19.2.dist-info/WHEEL
line_bot_sdk-3.19.2.dist-info/top_level.txt
line_bot_sdk-3.19.2.dist-info/RECORD
