Metadata-Version: 2.4
Name: line-bot-sdk
Version: 3.19.2
Summary: LINE Messaging API SDK for Python
Home-page: https://github.com/line/line-bot-sdk-python
Author: RyosukeHasebe
Author-email: hsb.1014@gmail.com
Maintainer: RyosukeHasebe
Maintainer-email: hsb.1014@gmail.com
License: Apache License 2.0
Classifier: Development Status :: 5 - Production/Stable
Classifier: License :: OSI Approved :: Apache Software License
Classifier: Intended Audience :: Developers
Classifier: Programming Language :: Python
Classifier: Programming Language :: Python :: 3.9
Classifier: Programming Language :: Python :: 3.10
Classifier: Programming Language :: Python :: 3.11
Classifier: Programming Language :: Python :: 3.12
Classifier: Programming Language :: Python :: 3.13
Classifier: Programming Language :: Python :: 3.14
Classifier: Topic :: Software Development
Requires-Python: >=3.9.0
License-File: LICENSE
Requires-Dist: requests<3,>=2.32.3
Requires-Dist: urllib3<3,>=2.0.5
Requires-Dist: aiohttp<4,>=3.10.9
Requires-Dist: future>=1.0.0
Requires-Dist: pydantic<3,>=2.0.3
Requires-Dist: aenum<4,>=3.1.11
Requires-Dist: python_dateutil<3,>=2.5.3
Requires-Dist: Deprecated>=1.2.18
Dynamic: author
Dynamic: author-email
Dynamic: classifier
Dynamic: description
Dynamic: home-page
Dynamic: license
Dynamic: license-file
Dynamic: maintainer
Dynamic: maintainer-email
Dynamic: requires-dist
Dynamic: requires-python
Dynamic: summary
